[1,["f6SJZOjTJB/JrJeh5xTdF7"],["_effectAsset"],[["cc.Material",["_states","_defines","_props"],1,12]],[[0,0,1,2,3]],[[0,[{"rasterizerState":{},"depthStencilState":{},"blendState":{"targets":[{}]}},{"rasterizerState":{},"depthStencilState":{},"blendState":{"targets":[{}]}},{"rasterizerState":{},"depthStencilState":{},"blendState":{"targets":[{}]}},{"rasterizerState":{},"depthStencilState":{},"blendState":{"targets":[{}]}}],[{"DCC_APP_NAME":2,"HAS_EXPORTED_METALLIC":true},{},{},{}],[[[{"emissiveScale":0,"shininessExponent":96.07843026347881,"specularFactor":0.5,"transparencyFactor":0},"mainColor",8,[4,4281479730],"emissive",8,[4,4281479730]],{},{},{}],11,0,0,0]]],0,0,[0],[0],[0]]
